LICENSE
witnessme/__init__.py
witnessme/api/__init__.py
witnessme/api/models.py
witnessme/api/routers/__init__.py
witnessme/api/routers/scan.py
witnessme/commands/__init__.py
witnessme/commands/grab.py
witnessme/commands/screenshot.py
witnessme/console/__init__.py
witnessme/console/witnessme.py
witnessme/console/wmapi.py
witnessme/console/wmdb.py
witnessme/database.py
witnessme/headlessbrowser.py
witnessme/parsers.py
witnessme/reporting.py
witnessme/signatures/ace_4710_device_manager.yaml
witnessme/signatures/admanager.yaml
witnessme/signatures/airos.yaml
witnessme/signatures/alienvault_usm_if_on_aws.yaml
witnessme/signatures/altova_license_server.yaml
witnessme/signatures/apache_lenya.yaml
witnessme/signatures/apache_tomcat.yaml
witnessme/signatures/apache_tomcat_default_page.yaml
witnessme/signatures/appinternals_xpert.yaml
witnessme/signatures/atutor_web_cms.yaml
witnessme/signatures/avamar_virtual_machine_proxy.yaml
witnessme/signatures/avaya_aura_system_manager_6_1.yaml
witnessme/signatures/avaya_b179.yaml
witnessme/signatures/avocent_dsr8035.yaml
witnessme/signatures/axeda_policy_server.yaml
witnessme/signatures/axistv_login.yaml
witnessme/signatures/barracuda_web_filter.yaml
witnessme/signatures/bitnami_redmine.yaml
witnessme/signatures/bomgar_device.yaml
witnessme/signatures/brother_8480dn.yaml
witnessme/signatures/brother_hl-2130.yaml
witnessme/signatures/brother_hl-2250dn.yaml
witnessme/signatures/brother_hl-2270dw.yaml
witnessme/signatures/brother_hl-5070n.yaml
witnessme/signatures/brother_hl-5350dn.yaml
witnessme/signatures/brother_hl-5370dw.yaml
witnessme/signatures/brother_ql-710w.yaml
witnessme/signatures/brother_ql-720.yaml
witnessme/signatures/buffalo_linkstation.yaml
witnessme/signatures/buffalo_pcast_media_nas_server.yaml
witnessme/signatures/buffalo_terastation.yaml
witnessme/signatures/ca_network_flow_analysis.yaml
witnessme/signatures/ca_performance_center.yaml
witnessme/signatures/cannon-ir-adv-c3530.yaml
witnessme-1.5.0.dist-info/entry_points.txt
witnessme-1.5.0.dist-info/LICENSE
witnessme-1.5.0.dist-info/WHEEL
witnessme-1.5.0.dist-info/METADATA
witnessme-1.5.0.dist-info/RECORD
