Metadata-Version: 2.1
Name: witnessme
Version: 1.5.0
Summary: Web Inventory tool that uses Pyppeteer (headless Chrome/Chromium) and provides some extra bells & whistles to make life easier.
Home-page: https://github.com/byt3bl33d3r/WitnessMe
License: GPL-3.0-only
Author: Marcello Salvati
Author-email: byt3bl33d3r@pm.com
Requires-Python: >=3.7.0,<4.0.0
Classifier: License :: OSI Approved :: GNU General Public License v3 (GPLv3)
Classifier: Programming Language :: Python :: 3
Classifier: Programming Language :: Python :: 3.7
Classifier: Programming Language :: Python :: 3.8
Classifier: Topic :: Security
Requires-Dist: aiodns (>=2.0.0,<3.0.0)
Requires-Dist: aiosqlite (>=0.13.0,<0.14.0)
Requires-Dist: fastapi (>=0.55.1,<0.56.0)
Requires-Dist: imgcat (>=0.5.0,<0.6.0)
Requires-Dist: jinja2 (>=2.11.2,<3.0.0)
Requires-Dist: lxml (>=4.5.2,<5.0.0)
Requires-Dist: prompt-toolkit (>=3.0.5,<4.0.0)
Requires-Dist: pydantic (>=1.5.1,<2.0.0)
Requires-Dist: pyppeteer (>=0.2.2,<0.3.0)
Requires-Dist: python-multipart (>=0.0.5,<0.0.6)
Requires-Dist: pyyaml (>=5.3.1,<6.0.0)
Requires-Dist: terminaltables (>=3.1.0,<4.0.0)
Requires-Dist: uvicorn (>=0.11.5,<0.12.0)
Requires-Dist: xmltodict (>=0.12.0,<0.13.0)
Project-URL: Repository, https://github.com/byt3bl33d3r/WitnessMe
